README.md
setup.py
najha/__init__.py
najha/functional.py
najha/sets.py
najha.egg-info/PKG-INFO
najha.egg-info/SOURCES.txt
najha.egg-info/dependency_links.txt
najha.egg-info/not-zip-safe
najha.egg-info/top_level.txt