Metadata-Version: 1.0
Name: najha
Version: 0.3
Summary: General purpose libraries for Python
Home-page: https://github.com/techiesse/najha
Author: Eric Chiesse
Author-email: techiesse@gmail.com
License: MIT
Platform: UNKNOWN
